{
  "library": "phosphor",
  "confidence": 0.7,
  "alternates": [],
  "stats": {
    "count": 4,
    "strokeOnly": 4,
    "fillOnly": 0,
    "mixed": 0,
    "avgStrokeWidth": 1.63,
    "gridDistribution": {
      "24": 4
    },
    "roundedCapsFraction": 1
  },
  "signals": [
    "strokeDominant",
    "roundedCaps",
    "grid24"
  ],
  "icons": [
    {
      "class": "",
      "grid": 24,
      "strokeWidth": 1.5,
      "style": "stroke"
    },
    {
      "class": "",
      "grid": 24,
      "strokeWidth": 1.5,
      "style": "stroke"
    },
    {
      "class": "",
      "grid": 24,
      "strokeWidth": 1.5,
      "style": "stroke"
    },
    {
      "class": "",
      "grid": 24,
      "strokeWidth": 2,
      "style": "stroke"
    }
  ]
}